djangocms_alias/__init__.py
djangocms_alias/admin.py
djangocms_alias/apps.py
djangocms_alias/cms_config.py
djangocms_alias/cms_menus.py
djangocms_alias/cms_plugins.py
djangocms_alias/cms_toolbars.py
djangocms_alias/cms_wizards.py
djangocms_alias/constants.py
djangocms_alias/filters.py
djangocms_alias/forms.py
djangocms_alias/internal_search.py
djangocms_alias/models.py
djangocms_alias/rendering.py
djangocms_alias/utils.py
djangocms_alias/views.py
djangocms_alias/locale/de/LC_MESSAGES/django.mo
djangocms_alias/locale/de/LC_MESSAGES/django.po
djangocms_alias/locale/en/LC_MESSAGES/django.mo
djangocms_alias/locale/en/LC_MESSAGES/django.po
djangocms_alias/locale/nl/LC_MESSAGES/django.mo
djangocms_alias/locale/nl/LC_MESSAGES/django.po
djangocms_alias/locale/sq/LC_MESSAGES/django.mo
djangocms_alias/locale/sq/LC_MESSAGES/django.po
djangocms_alias/migrations/0001_initial.py
djangocms_alias/migrations/0002_auto_20200723_1424.py
djangocms_alias/migrations/0003_auto_20230725_1547.py
djangocms_alias/migrations/0004_alter_aliascontent_language.py
djangocms_alias/migrations/0005_dynamic_slot_names.py
djangocms_alias/migrations/0006_alter_alias_id_alter_aliascontent_id_and_more.py
djangocms_alias/migrations/0007_alter_category_options_alter_aliasplugin_alias.py
djangocms_alias/migrations/__init__.py
djangocms_alias/static/djangocms_alias/js/alias_plugin.js
djangocms_alias/static/djangocms_alias/js/create.js
djangocms_alias/static/djangocms_alias/js/databridge.js
djangocms_alias/templates/admin/djangocms_alias/alias/change_form.html
djangocms_alias/templates/admin/djangocms_alias/alias/delete_confirmation.html
djangocms_alias/templates/admin/djangocms_alias/aliascontent/change_form.html
djangocms_alias/templates/djangocms_alias/add_alias.html
djangocms_alias/templates/djangocms_alias/alias_content.html
djangocms_alias/templates/djangocms_alias/alias_content_preview.html
djangocms_alias/templates/djangocms_alias/alias_recursive.html
djangocms_alias-3.0.3.dist-info/licenses/LICENSE.txt
djangocms_alias-3.0.3.dist-info/METADATA
djangocms_alias-3.0.3.dist-info/WHEEL
djangocms_alias-3.0.3.dist-info/top_level.txt
djangocms_alias-3.0.3.dist-info/RECORD
