Metadata-Version: 2.4
Name: djangocms-alias
Version: 3.0.3
Summary: An alias is a collection of plugins that is managed centrally.
Author-email: Divio AG <info@divio.ch>
Maintainer-email: Django CMS Association and contributors <info@django-cms.org>
License-Expression: BSD-3-Clause
Project-URL: Homepage, https://github.com/django-cms/djangocms-alias
Project-URL: Repository, https://github.com/django-cms/djangocms-alias
Project-URL: Documentation, https://github.com/django-cms/djangocms-alias
Project-URL: Bug Tracker, https://github.com/django-cms/djangocms-alias/issues
Keywords: django,django-cms,alias,plugins
Classifier: Environment :: Web Environment
Classifier: Framework :: Django
Classifier: Framework :: Django :: 4.2
Classifier: Framework :: Django :: 5.0
Classifier: Framework :: Django :: 5.1
Classifier: Framework :: Django :: 5.2
Classifier: Framework :: Django :: 6.0
Classifier: Framework :: Django CMS :: 5.0
Classifier: Intended Audience :: Developers
Classifier: Operating System :: OS Independent
Classifier: Programming Language :: Python
Classifier: Programming Language :: Python :: 3.10
Classifier: Programming Language :: Python :: 3.11
Classifier: Programming Language :: Python :: 3.12
Classifier: Programming Language :: Python :: 3.13
Classifier: Topic :: Internet :: WWW/HTTP :: Dynamic Content
Classifier: Topic :: Software Development
Classifier: Topic :: Software Development :: Libraries :: Application Frameworks
Requires-Python: >=3.10
License-File: LICENSE.txt
Requires-Dist: django-parler>=1.4
Requires-Dist: django-cms>=5.0
Dynamic: license-file
